{"6c:f3:7f:b8:ab:41": "Marts 102C", "6c:f3:7f:b8:ab:40": "Marts 102C", "6c:f3:7f:b8:ab:42": "Marts 102C", "00:1a:1e:22:3a:b0": "Coleman 1st Floor", "6c:f3:7f:b8:b0:a2": "Marts 118", "6c:f3:7f:b8:b0:a1": "Marts 118", "6c:f3:7f:b8:b0:a0": "Marts 118", "6c:f3:7f:e5:09:3a": "Dana 339", "00:1a:1e:22:55:41": "Olin 153C", "6c:f3:7f:b8:ab:f2": "CC 1st Floor", "6c:f3:7f:b8:ab:f1": "CC 1st Floor", "6c:f3:7f:b8:ab:f0": "CC 1st Floor", "00:1a:1e:22:3a:a2": "Coleman 1st Floor", "6c:f3:7f:e5:09:38": "Dana 339", "6c:f3:7f:e5:09:39": "Dana 339", "24:de:c6:06:4d:61": "Vaughn 201", "24:de:c6:06:4d:60": "Vaughn 201", "24:de:c6:06:4d:62": "Vaughn 201", "6c:f3:7f:e5:09:30": "Dana 339", "6c:f3:7f:e5:09:31": "Dana 339", "6c:f3:7f:e5:09:32": "Dana 339", "00:1a:1e:22:55:40": "Olin 153C", "24:de:c6:07:b7:42": "Vaughn 120", "00:1a:1e:22:1a:81": "Olin 1st Floor", "00:1a:1e:22:1a:80": "Olin 1st Floor", "00:1a:1e:22:1a:82": "Olin 1st Floor", "00:1a:1e:12:97:20": "CC Ground Floor", "00:1a:1e:12:97:21": "CC Ground Floor", "00:1a:1e:12:97:23": "CC Ground Floor", "00:1a:1e:22:35:32": "Dana 111A", "00:1a:1e:22:35:30": "Dana 111A", "00:1a:1e:22:35:31": "Dana 111A", "00:1a:1e:12:97:51": "Dana 134", "00:1a:1e:22:30:92": "Dana 221", "00:1a:1e:22:30:91": "Dana 221", "00:1a:1e:22:48:00": "Breakiron 071", "d8:c7:c8:a1:d4:da": "O'Leary 2nd Floor", "00:1a:1e:22:2e:61": "Coleman Ground Floor", "d8:c7:c8:a1:d8:12": "Freas Ground Floor", "d8:c7:c8:a1:d8:11": "Freas Ground Floor", "d8:c7:c8:a1:d8:10": "Freas Ground Floor", "00:1a:1e:22:2b:a0": "Rooke 010", "00:1a:1e:22:2b:a1": "Rooke 010", "00:1a:1e:22:2b:a2": "Rooke 010", "00:1a:1e:22:32:d2": "Rooke 1st Floor", "00:1a:1e:22:3d:80": "Olin 3rd Floor", "6c:f3:7f:b8:ac:10": "Olin 268", "00:1a:1e:22:3d:82": "Olin 3rd Floor", "6c:f3:7f:b8:ac:12": "Olin 268", "00:1a:1e:22:32:d1": "Rooke 1st Floor", "00:1a:1e:22:55:52": "Olin 153C", "00:1a:1e:22:55:50": "Olin 153C", "00:1a:1e:22:55:51": "Olin 153C", "00:1a:1e:22:39:d2": "Rooke 317", "00:1a:1e:22:39:d1": "Rooke 317", "00:1a:1e:22:39:d0": "Rooke 317", "00:1a:1e:23:98:b1": "Coleman 166", "00:1a:1e:23:98:b0": "Coleman 166", "6c:f3:7f:b8:ad:82": "Vaughn 237", "00:1a:1e:22:57:40": "Coleman Ground Floor", "00:1a:1e:22:56:b2": "Dana 134", "6c:f3:7f:b8:ad:81": "Vaughn 237", "00:1a:1e:22:56:b0": "Dana 134", "00:1a:1e:22:56:b1": "Dana 134", "6c:f3:7f:b8:ad:80": "Vaughn 237", "00:1a:1e:22:51:a2": "Dana 137", "00:1a:1e:22:51:a0": "Dana 137", "00:1a:1e:22:51:a1": "Dana 137", "6c:f3:7f:b8:ac:82": "Marts 2nd Floor", "6c:f3:7f:b8:ac:80": "Marts 2nd Floor", "6c:f3:7f:b8:ac:81": "Marts 2nd Floor", "00:1a:1e:22:2e:42": "Coleman 1st Floor", "00:1a:1e:22:2e:40": "Coleman 1st Floor", "00:1a:1e:22:2e:41": "Coleman 1st Floor", "00:1a:1e:22:2d:a1": "Olin 363C", "d8:c7:c8:a1:d4:d0": "O'Leary 2nd Floor", "d8:c7:c8:a1:d4:d1": "O'Leary 2nd Floor", "d8:c7:c8:a1:d4:d2": "O'Leary 2nd Floor", "6c:f3:7f:b8:ac:d1": "Marts 218C", "d8:c7:c8:a1:d8:1a": "Freas Ground Floor", "00:1a:1e:22:54:92": "Breakiron 068", "d8:c7:c8:a1:d4:d8": "O'Leary 2nd Floor", "d8:c7:c8:a1:d4:d9": "O'Leary 2nd Floor", "00:1a:1e:23:94:42": "Coleman 2nd Floor", "00:1a:1e:23:94:41": "Coleman 2nd Floor", "00:1a:1e:23:94:40": "Coleman 2nd Floor", "00:1a:1e:22:30:c1": "Dana 132", "00:1a:1e:22:30:c0": "Dana 132", "00:1a:1e:22:30:c2": "Dana 132", "00:1a:1e:22:4e:62": "Breakiron 164", "00:1a:1e:22:4e:60": "Breakiron 164", "00:1a:1e:22:4e:61": "Breakiron 164", "d8:c7:c8:a1:ce:d9": "Freas Ground Floor", "00:1a:1e:22:32:51": "Rooke 226", "d8:c7:c8:a1:c5:da": "O'Leary 216", "00:1a:1e:22:32:52": "Rooke 226", "6c:f3:7f:b8:af:62": "Marts 209C", "6c:f3:7f:b8:af:61": "Marts 209C", "6c:f3:7f:b8:af:60": "Marts 209C", "00:1a:1e:22:2f:61": "Rooke 335", "00:1a:1e:22:2f:60": "Rooke 335", "00:1a:1e:22:2f:62": "Rooke 335", "d8:c7:c8:a1:c5:d8": "O'Leary 216", "d8:c7:c8:a1:c5:d9": "O'Leary 216", "d8:c7:c8:a1:c5:d0": "O'Leary 216", "d8:c7:c8:a1:c5:d1": "O'Leary 216", "d8:c7:c8:a1:c5:d2": "O'Leary 216", "24:de:c6:04:38:41": "Vaughn 229", "24:de:c6:07:b7:52": "Vaughn 120", "24:de:c6:07:b7:50": "Vaughn 120", "24:de:c6:07:b7:51": "Vaughn 120", "00:1a:1e:22:2d:c0": "Rooke 216", "00:1a:1e:22:2d:c1": "Rooke 216", "00:1a:1e:22:2d:c2": "Rooke 216", "00:1a:1e:22:48:10": "Breakiron 071", "00:1a:1e:22:2c:40": "Coleman Ground Floor", "00:1a:1e:22:2c:41": "Coleman Ground Floor", "00:1a:1e:22:2c:42": "Coleman Ground Floor", "00:1a:1e:22:48:11": "Breakiron 071", "00:1a:1e:22:30:82": "Dana 221", "6c:f3:7f:b8:b0:71": "Olin 268", "6c:f3:7f:b8:b0:70": "Olin 268", "6c:f3:7f:b8:b0:72": "Olin 268", "00:1a:1e:22:55:c0": "Dana 115", "00:1a:1e:22:55:c1": "Dana 115", "00:1a:1e:22:55:c2": "Dana 115", "24:de:c6:04:38:40": "Vaughn 229", "6c:f3:7f:e5:09:01": "Dana 329", "6c:f3:7f:e5:09:00": "Dana 329", "6c:f3:7f:e5:09:02": "Dana 329", "6c:f3:7f:e5:09:09": "Dana 329", "6c:f3:7f:e5:09:08": "Dana 329", "00:1a:1e:22:54:02": "Breakiron 370", "00:1a:1e:22:54:00": "Breakiron 370", "00:1a:1e:22:54:01": "Breakiron 370", "00:1a:1e:22:43:02": "Dana 245", "00:1a:1e:22:43:00": "Dana 245", "00:1a:1e:22:43:01": "Dana 245", "00:1a:1e:22:15:81": "Coleman 119", "00:1a:1e:22:15:80": "Coleman 119", "24:de:c6:04:38:42": "Vaughn 229", "00:1a:1e:22:15:82": "Coleman 119", "00:1a:1e:22:2c:f2": "Olin 255", "00:1a:1e:22:2c:f0": "Olin 255", "00:1a:1e:22:2c:f1": "Olin 255", "24:de:c6:06:4d:a0": "Vaughn 2nd Floor", "24:de:c6:06:4d:a1": "Vaughn 2nd Floor", "24:de:c6:06:4d:a2": "Vaughn 2nd Floor", "00:1a:1e:22:34:f2": "Coleman 2nd Floor", "00:1a:1e:22:34:f0": "Coleman 2nd Floor", "00:1a:1e:22:34:f1": "Coleman 2nd Floor", "d8:c7:c8:a1:c5:ba": "O'Leary 308", "00:1a:1e:22:3e:82": "Rooke 301", "00:1a:1e:22:3e:81": "Rooke 301", "00:1a:1e:22:3e:80": "Rooke 301", "00:1a:1e:23:99:a2": "Olin 266", "00:1a:1e:23:99:a1": "Olin 266", "00:1a:1e:23:99:a0": "Olin 266", "6c:f3:7f:e5:09:0a": "Dana 329", "00:1a:1e:22:34:31": "Olin 275", "00:1a:1e:23:9c:f1": "Coleman 1st Floor", "00:1a:1e:22:3b:80": "Coleman 150", "00:1a:1e:22:3b:81": "Coleman 150", "00:1a:1e:22:34:32": "Olin 275", "00:1a:1e:22:2b:b1": "Rooke 010", "00:1a:1e:22:2b:b0": "Rooke 010", "00:1a:1e:22:2b:b2": "Rooke 010", "00:1a:1e:22:48:02": "Breakiron 071", "00:1a:1e:22:46:f2": "Coleman 121", "00:1a:1e:22:46:f1": "Coleman 121", "00:1a:1e:22:46:f0": "Coleman 121", "00:1a:1e:22:4f:c0": "Olin 379C", "00:1a:1e:22:4f:c1": "Olin 379C", "6c:f3:7f:e6:ba:e9": "O'Leary 206", "6c:f3:7f:e6:ba:e8": "O'Leary 206", "6c:f3:7f:e6:ba:e2": "O'Leary 206", "6c:f3:7f:e6:ba:e1": "O'Leary 206", "6c:f3:7f:e6:ba:e0": "O'Leary 206", "6c:f3:7f:b8:a7:91": "Breakiron B76", "6c:f3:7f:b8:a7:90": "Breakiron B76", "00:1a:1e:23:9c:f2": "Coleman 1st Floor", "6c:f3:7f:b8:a7:92": "Breakiron B76", "00:1a:1e:22:51:f2": "Coleman 060", "00:1a:1e:22:51:f1": "Coleman 060", "00:1a:1e:22:51:f0": "Coleman 060", "00:1a:1e:22:56:71": "Breakiron 269", "00:1a:1e:22:56:70": "Breakiron 269", "00:1a:1e:22:32:c1": "Rooke 1st Floor", "00:1a:1e:22:56:72": "Breakiron 269", "d8:c7:c8:a1:ce:da": "Freas Ground Floor", "00:1a:1e:22:56:00": "Rooke 323", "00:1a:1e:22:56:01": "Rooke 323", "00:1a:1e:22:56:02": "Rooke 323", "6c:f3:7f:b8:ac:c0": "Marts 218C", "00:1a:1e:22:33:92": "Rooke Ground Floor", "00:1a:1e:22:33:90": "Rooke Ground Floor", "00:1a:1e:22:33:91": "Rooke Ground Floor", "00:1a:1e:22:39:72": "Dana 132", "00:1a:1e:22:39:70": "Dana 132", "00:1a:1e:22:39:71": "Dana 132", "00:1a:1e:23:9d:00": "Coleman Ground Floor", "00:1a:1e:22:2d:b0": "Olin 363C", "6c:f3:7f:b8:ab:50": "Marts 102C", "6c:f3:7f:b8:ab:51": "Marts 102C", "00:1a:1e:23:99:c0": "Coleman 2nd Floor", "24:de:c6:07:b7:40": "Vaughn 120", "00:1a:1e:22:2d:b1": "Olin 363C", "6c:f3:7f:e6:ba:ea": "O'Leary 206", "6c:f3:7f:b8:ac:11": "Olin 268", "00:1a:1e:22:3a:72": "Dana 321", "00:1a:1e:22:3a:21": "Breakiron 266", "00:1a:1e:22:3a:20": "Breakiron 266", "00:1a:1e:22:3a:22": "Breakiron 266", "00:1a:1e:22:3a:70": "Dana 321", "d8:c7:c8:a1:ce:d0": "Freas Ground Floor", "d8:c7:c8:a1:ce:d1": "Freas Ground Floor", "d8:c7:c8:a1:ce:d2": "Freas Ground Floor", "00:1a:1e:22:3a:71": "Dana 321", "00:1a:1e:23:95:51": "Olin 464", "00:1a:1e:23:95:50": "Olin 464", "00:1a:1e:23:9b:e2": "Coleman 2nd Floor", "00:1a:1e:23:9b:e0": "Coleman 2nd Floor", "00:1a:1e:23:9b:e1": "Coleman 2nd Floor", "24:de:c6:06:4d:72": "Vaughn 201", "24:de:c6:06:4d:70": "Vaughn 201", "24:de:c6:06:4d:71": "Vaughn 201", "00:24:6c:87:64:82": "Rooke 207", "00:24:6c:87:64:81": "Rooke 207", "00:24:6c:87:64:80": "Rooke 207", "00:1a:1e:22:2c:52": "Coleman Ground Floor", "00:24:6c:87:64:89": "Rooke 207", "00:24:6c:87:64:88": "Rooke 207", "00:1a:1e:22:2c:51": "Coleman Ground Floor", "00:1a:1e:22:1a:92": "Olin 1st Floor", "00:1a:1e:22:1a:90": "Olin 1st Floor", "00:1a:1e:22:1a:91": "Olin 1st Floor", "00:24:6c:87:64:8a": "Rooke 207", "00:1a:1e:22:35:02": "Olin 451", "00:1a:1e:22:35:01": "Olin 451", "00:1a:1e:22:35:00": "Olin 451", "00:1a:1e:22:3e:42": "CC 107", "00:1a:1e:22:3e:41": "CC 107", "00:1a:1e:22:3e:40": "CC 107", "00:1a:1e:22:33:41": "Olin 271C", "00:1a:1e:22:33:40": "Olin 271C", "00:1a:1e:22:33:42": "Olin 271C", "00:1a:1e:12:97:42": "Dana 134", "00:1a:1e:12:97:40": "Dana 134", "00:1a:1e:12:97:41": "Dana 134", "00:1a:1e:22:30:80": "Dana 221", "00:1a:1e:22:30:81": "Dana 221", "00:1a:1e:22:48:12": "Breakiron 071", "24:de:c6:06:4d:b1": "Vaughn 2nd Floor", "24:de:c6:06:4d:b0": "Vaughn 2nd Floor", "24:de:c6:06:4d:b2": "Vaughn 2nd Floor", "6c:f3:7f:b8:ac:02": "Olin 268", "00:1a:1e:22:34:30": "Olin 275", "6c:f3:7f:b8:ac:00": "Olin 268", "6c:f3:7f:b8:ac:01": "Olin 268", "00:1a:1e:22:2e:c2": "Coleman Ground Floor", "d8:c7:c8:a1:c6:68": "O'Leary 106", "00:1a:1e:22:55:62": "Rooke 116", "00:1a:1e:22:55:61": "Rooke 116", "00:1a:1e:22:55:60": "Rooke 116", "00:1a:1e:22:2f:72": "Rooke 335", "00:1a:1e:23:99:d0": "Coleman 2nd Floor", "00:1a:1e:22:56:a2": "Dana 134", "00:1a:1e:22:56:a1": "Dana 134", "00:1a:1e:22:56:a0": "Dana 134", "00:1a:1e:11:96:91": "Dana 304", "00:1a:1e:11:96:90": "Dana 304", "00:1a:1e:11:96:92": "Dana 304", "00:1a:1e:22:2e:72": "Coleman Ground Floor", "00:1a:1e:22:2e:71": "Coleman Ground Floor", "00:1a:1e:22:2e:70": "Coleman Ground Floor", "00:1a:1e:22:2a:d2": "Rooke 018", "00:1a:1e:22:2a:d0": "Rooke 018", "00:1a:1e:22:2a:d1": "Rooke 018", "00:1a:1e:22:3f:32": "Coleman 1st Floor", "00:1a:1e:22:3f:31": "Coleman 1st Floor", "00:1a:1e:22:3f:30": "Coleman 1st Floor", "00:1a:1e:22:30:b2": "Vaughn Ground Floor", "00:1a:1e:23:9c:e0": "Coleman 1st Floor", "00:1a:1e:22:30:b0": "Vaughn Ground Floor", "00:1a:1e:22:30:b1": "Vaughn Ground Floor", "00:1a:1e:22:2e:c0": "Coleman Ground Floor", "00:1a:1e:22:32:42": "Rooke 226", "6c:f3:7f:b8:aa:52": "Marts 1st Floor", "00:1a:1e:22:32:40": "Rooke 226", "00:1a:1e:22:32:41": "Rooke 226", "00:1a:1e:22:51:b2": "Dana 137", "00:1a:1e:22:51:b1": "Dana 137", "00:1a:1e:22:51:b0": "Dana 137", "00:1a:1e:22:56:31": "Dana Ground Floor", "00:1a:1e:22:56:30": "Dana Ground Floor", "00:1a:1e:22:56:32": "Dana Ground Floor", "6c:f3:7f:b8:af:70": "Marts 209C", "00:1a:1e:22:39:02": "Breakiron 368", "00:1a:1e:22:39:01": "Breakiron 368", "00:1a:1e:22:39:00": "Breakiron 368", "00:1a:1e:23:99:71": "Olin 4th Floor", "00:1a:1e:23:99:70": "Olin 4th Floor", "00:1a:1e:22:2f:70": "Rooke 335", "00:1a:1e:23:99:72": "Olin 4th Floor", "6c:f3:7f:b8:ad:b1": "Marts 220C", "d8:c7:c8:a1:24:9a": "Rooke 203", "d8:c7:c8:a1:c6:12": "O'Leary 304", "d8:c7:c8:a1:c6:10": "O'Leary 304", "d8:c7:c8:a1:c6:11": "O'Leary 304", "00:1a:1e:22:2d:d1": "Rooke 216", "00:1a:1e:22:2d:d0": "Rooke 216", "00:1a:1e:22:2d:d2": "Rooke 216", "00:1a:1e:23:9c:e1": "Coleman 1st Floor", "d8:c7:c8:a1:c6:18": "O'Leary 304", "d8:c7:c8:a1:c6:19": "O'Leary 304", "00:1a:1e:22:3b:82": "Coleman 150", "00:1a:1e:23:94:51": "Coleman 2nd Floor", "00:1a:1e:23:94:52": "Coleman 2nd Floor", "00:1a:1e:23:9c:e2": "Coleman 1st Floor", "6c:f3:7f:b8:b0:62": "Olin 268", "6c:f3:7f:b8:b0:60": "Olin 268", "6c:f3:7f:b8:b0:61": "Olin 268", "00:24:6c:af:f9:91": "Vaughn 1st Floor", "00:24:6c:af:f9:90": "Vaughn 1st Floor", "00:24:6c:af:f9:92": "Vaughn 1st Floor", "00:1a:1e:22:53:21": "Dana 150", "00:1a:1e:22:53:20": "Dana 150", "00:1a:1e:22:53:22": "Dana 150", "00:24:6c:af:f9:99": "Vaughn 1st Floor", "00:24:6c:af:f9:98": "Vaughn 1st Floor", "00:1a:1e:22:3a:a1": "Coleman 1st Floor", "d8:c7:c8:a1:c6:1a": "O'Leary 304", "00:1a:1e:12:97:50": "Dana 134", "d8:c7:c8:a1:d6:30": "O'Leary 101", "00:1a:1e:22:48:01": "Breakiron 071", "00:1a:1e:22:30:90": "Dana 221", "d8:c7:c8:a1:24:91": "Rooke 203", "d8:c7:c8:a1:24:90": "Rooke 203", "d8:c7:c8:a1:24:92": "Rooke 203", "d8:c7:c8:a1:24:99": "Rooke 203", "d8:c7:c8:a1:24:98": "Rooke 203", "00:1a:1e:22:15:90": "Coleman 119", "00:1a:1e:23:9d:02": "Coleman Ground Floor", "00:24:6c:af:f9:9a": "Vaughn 1st Floor", "00:1a:1e:22:2c:e2": "Olin 255", "00:1a:1e:22:2c:e1": "Olin 255", "00:1a:1e:22:2c:e0": "Olin 255", "00:1a:1e:22:2e:d2": "Coleman Ground Floor", "00:1a:1e:22:34:e2": "Coleman 2nd Floor", "00:1a:1e:22:34:e1": "Coleman 2nd Floor", "00:1a:1e:22:34:e0": "Coleman 2nd Floor", "00:1a:1e:22:3e:90": "Rooke 301", "00:1a:1e:22:3e:91": "Rooke 301", "00:1a:1e:22:3e:92": "Rooke 301", "00:1a:1e:22:3a:a0": "Coleman 1st Floor", "6c:f3:7f:b8:ae:12": "Marts 217D", "6c:f3:7f:b8:ae:11": "Marts 217D", "6c:f3:7f:b8:ae:10": "Marts 217D", "00:1a:1e:22:4f:c2": "Olin 379C", "00:1a:1e:22:43:11": "Dana 245", "00:1a:1e:22:43:10": "Dana 245", "00:1a:1e:23:94:50": "Coleman 2nd Floor", "6c:f3:7f:b8:aa:51": "Marts 1st Floor", "00:1a:1e:22:57:42": "Coleman Ground Floor", "00:1a:1e:22:57:41": "Coleman Ground Floor", "6c:f3:7f:b8:aa:50": "Marts 1st Floor", "00:1a:1e:22:2c:92": "Dana 2nd Floor", "00:1a:1e:22:2c:91": "Dana 2nd Floor", "00:1a:1e:22:2c:90": "Dana 2nd Floor", "00:1a:1e:22:2e:32": "Olin 182C", "00:1a:1e:22:2e:31": "Olin 182C", "00:1a:1e:22:2e:30": "Olin 182C", "00:1a:1e:22:4f:d1": "Olin 379C", "00:1a:1e:22:4f:d0": "Olin 379C", "00:1a:1e:22:4f:d2": "Olin 379C", "00:1a:1e:23:9c:f0": "Coleman 1st Floor", "6c:f3:7f:b8:a7:82": "Breakiron B76", "6c:f3:7f:b8:a7:80": "Breakiron B76", "6c:f3:7f:b8:a7:81": "Breakiron B76", "00:1a:1e:22:56:d0": "CC 204", "00:1a:1e:22:56:d1": "CC 204", "00:1a:1e:22:56:d2": "CC 204", "00:1a:1e:22:3d:81": "Olin 3rd Floor", "00:1a:1e:22:56:62": "Breakiron 269", "00:1a:1e:22:56:60": "Breakiron 269", "00:1a:1e:22:56:61": "Breakiron 269", "00:1a:1e:22:32:b0": "Rooke 108", "00:1a:1e:22:32:b1": "Rooke 108", "00:1a:1e:22:32:b2": "Rooke 108", "6c:f3:7f:b8:a7:11": "CC 202", "6c:f3:7f:b8:a7:10": "CC 202", "6c:f3:7f:b8:a7:12": "CC 202", "00:1a:1e:22:15:92": "Coleman 119", "00:1a:1e:22:2a:c2": "Rooke 018", "00:1a:1e:22:2a:c1": "Rooke 018", "00:1a:1e:22:2a:c0": "Rooke 018", "6c:f3:7f:b8:ac:b0": "Marts 07", "6c:f3:7f:b8:ac:b1": "Marts 07", "6c:f3:7f:b8:ac:b2": "Marts 07", "00:1a:1e:22:41:71": "Rooke 102", "00:1a:1e:22:41:70": "Rooke 102", "00:1a:1e:22:41:72": "Rooke 102", "6c:f3:7f:b8:ac:a2": "Marts 07", "00:1a:1e:23:95:40": "Olin 464", "00:1a:1e:23:95:41": "Olin 464", "00:1a:1e:23:95:42": "Olin 464", "6c:f3:7f:b8:ad:90": "Vaughn 237", "6c:f3:7f:b8:af:71": "Marts 209C", "6c:f3:7f:b8:af:72": "Marts 209C", "00:1a:1e:22:32:c2": "Rooke 1st Floor", "d8:c7:c8:a1:da:3a": "Dana 335", "6c:f3:7f:b8:a8:61": "Olin 261", "6c:f3:7f:b8:a8:60": "Olin 261", "6c:f3:7f:b8:a8:62": "Olin 261", "6c:f3:7f:b8:af:41": "Marts 230", "6c:f3:7f:b8:af:40": "Marts 230", "00:1a:1e:23:9d:01": "Coleman Ground Floor", "6c:f3:7f:b8:af:42": "Marts 230", "24:de:c6:04:35:72": "Vaughn Ground Floor", "00:1a:1e:22:3a:32": "Breakiron 266", "00:1a:1e:22:2d:a2": "Olin 363C", "00:1a:1e:22:3a:30": "Breakiron 266", "00:1a:1e:22:3a:31": "Breakiron 266", "00:1a:1e:22:2d:a0": "Olin 363C", "d8:c7:c8:a1:da:38": "Dana 335", "d8:c7:c8:a1:da:39": "Dana 335", "00:1a:1e:23:9b:f2": "Coleman 2nd Floor", "00:1a:1e:23:9b:f1": "Coleman 2nd Floor", "00:1a:1e:23:9b:f0": "Coleman 2nd Floor", "d8:c7:c8:a1:da:32": "Dana 335", "d8:c7:c8:a1:da:30": "Dana 335", "d8:c7:c8:a1:da:31": "Dana 335", "00:1a:1e:22:2f:71": "Rooke 335", "00:1a:1e:23:98:b2": "Coleman 166", "00:1a:1e:22:55:a2": "Rooke 3rd Floor", "00:1a:1e:22:3a:61": "Dana 321", "00:1a:1e:22:55:a0": "Rooke 3rd Floor", "00:1a:1e:22:55:a1": "Rooke 3rd Floor", "00:1a:1e:22:3a:60": "Dana 321", "00:1a:1e:22:3a:62": "Dana 321", "d8:c7:c8:a1:d8:19": "Freas Ground Floor", "00:1a:1e:22:3b:b0": "Dana 033", "00:1a:1e:22:3b:b1": "Dana 033", "00:1a:1e:22:3b:b2": "Dana 033", "6c:f3:7f:b8:ac:c2": "Marts 218C", "00:1a:1e:22:3e:50": "CC 107", "00:1a:1e:22:3e:51": "CC 107", "00:1a:1e:22:3e:52": "CC 107", "00:1a:1e:22:33:52": "Olin 271C", "6c:f3:7f:b8:ac:c1": "Marts 218C", "00:1a:1e:22:33:50": "Olin 271C", "00:1a:1e:22:33:51": "Olin 271C", "d8:c7:c8:a1:d8:18": "Freas Ground Floor", "d8:c7:c8:a1:24:7a": "Dana 010", "d8:c7:c8:a1:bd:6a": "Freas Ground Floor", "24:de:c6:04:35:62": "Vaughn Ground Floor", "24:de:c6:04:35:61": "Vaughn Ground Floor", "24:de:c6:04:35:60": "Vaughn Ground Floor", "00:1a:1e:22:34:22": "Olin 275", "00:1a:1e:22:34:20": "Olin 275", "00:1a:1e:22:34:21": "Olin 275", "00:1a:1e:22:3f:20": "Coleman 1st Floor", "00:1a:1e:22:3f:21": "Coleman 1st Floor", "00:1a:1e:22:3f:22": "Coleman 1st Floor", "00:1a:1e:23:99:c2": "Coleman 2nd Floor", "00:1a:1e:22:2a:51": "Rooke 2nd Floor", "00:1a:1e:22:2a:50": "Rooke 2nd Floor", "00:1a:1e:22:2a:52": "Rooke 2nd Floor", "00:1a:1e:22:53:a0": "Dana 305", "00:1a:1e:22:53:a1": "Dana 305", "00:1a:1e:22:53:a2": "Dana 305", "00:1a:1e:12:97:52": "Dana 134", "00:1a:1e:11:96:82": "Dana 304", "00:1a:1e:11:96:80": "Dana 304", "00:1a:1e:11:96:81": "Dana 304", "00:1a:1e:22:3b:72": "Breakiron 167", "00:1a:1e:22:3b:71": "Breakiron 167", "00:1a:1e:22:3b:70": "Breakiron 167", "d8:c7:c8:a1:bd:68": "Freas Ground Floor", "d8:c7:c8:a1:bd:69": "Freas Ground Floor", "00:1a:1e:22:2e:62": "Coleman Ground Floor", "d8:c7:c8:a1:24:72": "Dana 010", "d8:c7:c8:a1:24:71": "Dana 010", "d8:c7:c8:a1:24:70": "Dana 010", "d8:c7:c8:a1:bd:60": "Freas Ground Floor", "d8:c7:c8:a1:bd:61": "Freas Ground Floor", "d8:c7:c8:a1:bd:62": "Freas Ground Floor", "00:1a:1e:22:54:91": "Breakiron 068", "00:1a:1e:22:54:90": "Breakiron 068", "d8:c7:c8:a1:24:79": "Dana 010", "d8:c7:c8:a1:24:78": "Dana 010", "00:1a:1e:22:2f:42": "Dana 224", "00:1a:1e:22:2f:41": "Dana 224", "00:1a:1e:22:2f:40": "Dana 224", "00:1a:1e:22:30:a2": "Vaughn Ground Floor", "00:1a:1e:22:30:a1": "Vaughn Ground Floor", "00:1a:1e:22:30:a0": "Vaughn Ground Floor", "00:1a:1e:22:32:a1": "Rooke 108", "00:1a:1e:22:32:a0": "Rooke 108", "00:1a:1e:22:32:a2": "Rooke 108", "00:1a:1e:22:35:21": "Dana 111A", "6c:f3:7f:b8:aa:40": "Marts 1st Floor", "6c:f3:7f:b8:aa:41": "Marts 1st Floor", "6c:f3:7f:b8:aa:42": "Marts 1st Floor", "00:1a:1e:22:3b:a0": "Dana 033", "00:1a:1e:22:56:22": "Dana Ground Floor", "00:1a:1e:22:56:20": "Dana Ground Floor", "00:1a:1e:22:56:21": "Dana Ground Floor", "6c:f3:7f:b8:ac:a1": "Marts 07", "6c:f3:7f:b8:ac:a0": "Marts 07", "00:1a:1e:22:35:22": "Dana 111A", "00:1a:1e:22:26:61": "Breakiron B60", "00:1a:1e:22:26:60": "Breakiron B60", "00:1a:1e:22:26:62": "Breakiron B60", "00:1a:1e:22:39:10": "Breakiron 368", "00:1a:1e:22:39:11": "Breakiron 368", "00:1a:1e:22:39:12": "Breakiron 368", "00:24:6c:b6:fc:b2": "Freas Ground Floor", "00:1a:1e:22:39:c2": "Rooke 317", "6c:f3:7f:b8:ac:d2": "Marts 218C", "00:1a:1e:22:39:c0": "Rooke 317", "00:1a:1e:22:39:c1": "Rooke 317", "00:1a:1e:23:99:62": "Olin 4th Floor", "00:1a:1e:23:99:60": "Olin 4th Floor", "00:1a:1e:23:99:61": "Olin 4th Floor", "00:24:6c:b6:fc:b0": "Freas Ground Floor", "6c:f3:7f:b8:ac:d0": "Marts 218C", "d8:c7:c8:a1:c5:b8": "O'Leary 308", "d8:c7:c8:a1:c5:b9": "O'Leary 308", "d8:c7:c8:a1:c5:b2": "O'Leary 308", "d8:c7:c8:a1:c5:b0": "O'Leary 308", "d8:c7:c8:a1:c5:b1": "O'Leary 308", "6c:f3:7f:b8:b0:b2": "Marts 118", "6c:f3:7f:b8:b0:b0": "Marts 118", "6c:f3:7f:b8:b0:b1": "Marts 118", "6c:f3:7f:b8:ab:e2": "CC 1st Floor", "6c:f3:7f:b8:ab:e0": "CC 1st Floor", "6c:f3:7f:b8:ab:e1": "CC 1st Floor", "00:1a:1e:22:53:32": "Dana 150", "00:1a:1e:22:53:30": "Dana 150", "00:1a:1e:22:53:31": "Dana 150", "6c:f3:7f:b8:ad:a0": "Marts 220C", "6c:f3:7f:b8:ad:a1": "Marts 220C", "6c:f3:7f:b8:ad:a2": "Marts 220C", "24:de:c6:04:38:50": "Vaughn 229", "00:24:6c:b6:fc:ba": "Freas Ground Floor", "d8:c7:c8:a1:d9:c2": "Freas 06", "d8:c7:c8:a1:24:68": "Rooke 207", "d8:c7:c8:a1:d9:c0": "Freas 06", "d8:c7:c8:a1:d9:c1": "Freas 06", "d8:c7:c8:a1:24:69": "Rooke 207", "d8:c7:c8:a1:d9:c8": "Freas 06", "d8:c7:c8:a1:d9:c9": "Freas 06", "00:1a:1e:12:97:33": "CC Ground Floor", "00:1a:1e:12:97:31": "CC Ground Floor", "00:1a:1e:12:97:30": "CC Ground Floor", "00:1a:1e:22:55:d1": "Dana 115", "00:1a:1e:22:55:d0": "Dana 115", "00:24:6c:b6:fc:b9": "Freas Ground Floor", "00:24:6c:b6:fc:b8": "Freas Ground Floor", "00:1a:1e:22:3b:a1": "Dana 033", "00:1a:1e:22:35:20": "Dana 111A", "00:1a:1e:22:3b:a2": "Dana 033", "00:1a:1e:22:35:10": "Olin 451", "00:24:6c:b6:fc:b1": "Freas Ground Floor", "00:1a:1e:22:55:d2": "Dana 115", "6c:f3:7f:b8:ae:00": "Marts 217D", "6c:f3:7f:b8:ae:01": "Marts 217D", "6c:f3:7f:b8:ae:02": "Marts 217D", "00:1a:1e:22:35:11": "Olin 451", "00:1a:1e:22:2e:60": "Coleman Ground Floor", "00:1a:1e:22:35:12": "Olin 451", "24:de:c6:04:35:70": "Vaughn Ground Floor", "00:1a:1e:22:57:50": "Coleman Ground Floor", "00:1a:1e:22:57:51": "Coleman Ground Floor", "00:1a:1e:22:57:52": "Coleman Ground Floor", "6c:f3:7f:b8:ad:91": "Vaughn 237", "6c:f3:7f:b8:ad:92": "Vaughn 237", "d8:c7:c8:a1:d9:ca": "Freas 06", "00:1a:1e:22:3d:92": "Olin 3rd Floor", "00:1a:1e:22:3d:91": "Olin 3rd Floor", "00:1a:1e:22:3d:90": "Olin 3rd Floor", "00:1a:1e:22:2c:80": "Dana 2nd Floor", "00:1a:1e:22:2c:81": "Dana 2nd Floor", "00:1a:1e:22:2c:82": "Dana 2nd Floor", "00:1a:1e:22:2e:20": "Olin 182C", "00:1a:1e:22:2e:21": "Olin 182C", "00:1a:1e:22:2e:22": "Olin 182C", "24:de:c6:04:35:71": "Vaughn Ground Floor", "00:1a:1e:22:53:b1": "Dana 305", "00:1a:1e:22:53:b0": "Dana 305", "d8:c7:c8:a1:d6:31": "O'Leary 101", "00:1a:1e:22:55:42": "Olin 153C", "d8:c7:c8:a1:d6:39": "O'Leary 101", "d8:c7:c8:a1:d6:38": "O'Leary 101", "00:1a:1e:22:56:c1": "CC 204", "00:1a:1e:22:56:c0": "CC 204", "00:1a:1e:22:56:c2": "CC 204", "6c:f3:7f:b8:ac:91": "Marts 2nd Floor", "d8:c7:c8:a1:ce:d8": "Freas Ground Floor", "6c:f3:7f:b8:ac:92": "Marts 2nd Floor", "6c:f3:7f:b8:a7:02": "CC 202", "6c:f3:7f:b8:a7:00": "CC 202", "6c:f3:7f:b8:a7:01": "CC 202", "00:1a:1e:22:2e:51": "Coleman 1st Floor", "00:1a:1e:22:2e:50": "Coleman 1st Floor", "00:1a:1e:22:2e:52": "Coleman 1st Floor", "00:1a:1e:22:41:62": "Rooke 102", "00:1a:1e:22:41:60": "Rooke 102", "00:1a:1e:22:41:61": "Rooke 102", "00:1a:1e:22:30:d0": "Dana 132", "00:1a:1e:22:30:d1": "Dana 132", "00:1a:1e:22:30:d2": "Dana 132", "00:1a:1e:22:4e:71": "Breakiron 164", "00:1a:1e:22:4e:70": "Breakiron 164", "00:1a:1e:22:32:d0": "Rooke 1st Floor", "00:1a:1e:22:4e:72": "Breakiron 164", "d8:c7:c8:a1:d6:3a": "O'Leary 101", "6c:f3:7f:b8:a8:72": "Olin 261", "6c:f3:7f:b8:a8:70": "Olin 261", "6c:f3:7f:b8:a8:71": "Olin 261", "6c:f3:7f:b8:af:52": "Marts 230", "6c:f3:7f:b8:af:50": "Marts 230", "6c:f3:7f:b8:af:51": "Marts 230", "00:1a:1e:23:9d:10": "Coleman Ground Floor", "00:1a:1e:23:9d:11": "Coleman Ground Floor", "00:1a:1e:23:9d:12": "Coleman Ground Floor", "d8:c7:c8:a1:c5:e2": "O'Leary 115", "d8:c7:c8:a1:c5:e1": "O'Leary 115", "d8:c7:c8:a1:c5:e0": "O'Leary 115", "24:de:c6:04:38:51": "Vaughn 229", "00:24:6c:af:f4:3a": "Dana 343", "00:1a:1e:22:2e:c1": "Coleman Ground Floor", "24:de:c6:04:38:52": "Vaughn 229", "24:de:c6:07:b7:41": "Vaughn 120", "00:1a:1e:22:2d:b2": "Olin 363C", "d8:c7:c8:a1:c5:e9": "O'Leary 115", "d8:c7:c8:a1:c5:e8": "O'Leary 115", "d8:c7:c8:a1:d5:58": "O'Leary 3rd Floor", "d8:c7:c8:a1:d5:59": "O'Leary 3rd Floor", "d8:c7:c8:a1:d5:50": "O'Leary 3rd Floor", "d8:c7:c8:a1:d5:51": "O'Leary 3rd Floor", "d8:c7:c8:a1:d5:52": "O'Leary 3rd Floor", "00:1a:1e:22:2c:50": "Coleman Ground Floor", "d8:c7:c8:a1:d6:32": "O'Leary 101", "d8:c7:c8:a1:c6:62": "O'Leary 106", "d8:c7:c8:a1:c6:61": "O'Leary 106", "d8:c7:c8:a1:c6:60": "O'Leary 106", "d8:c7:c8:a1:c4:9a": "O'Leary 221", "d8:c7:c8:a1:c6:69": "O'Leary 106", "00:1a:1e:22:53:b2": "Dana 305", "00:1a:1e:22:55:b2": "Rooke 3rd Floor", "00:1a:1e:22:55:b1": "Rooke 3rd Floor", "00:1a:1e:22:55:b0": "Rooke 3rd Floor", "00:1a:1e:22:15:91": "Coleman 119", "24:de:c6:07:c2:c2": "Marts 012", "6c:f3:7f:b8:ad:b0": "Marts 220C", "24:de:c6:07:c2:c0": "Marts 012", "24:de:c6:07:c2:c1": "Marts 012", "6c:f3:7f:b8:ad:b2": "Marts 220C", "d8:c7:c8:a1:d5:5a": "O'Leary 3rd Floor", "00:24:6c:af:f4:38": "Dana 343", "00:24:6c:af:f4:39": "Dana 343", "00:1a:1e:22:54:11": "Breakiron 370", "00:1a:1e:22:54:10": "Breakiron 370", "d8:c7:c8:a1:c5:ea": "O'Leary 115", "00:1a:1e:22:54:12": "Breakiron 370", "00:24:6c:af:f4:30": "Dana 343", "00:24:6c:af:f4:31": "Dana 343", "00:24:6c:af:f4:32": "Dana 343", "00:1a:1e:22:43:12": "Dana 245", "24:de:c6:07:c2:d2": "Marts 012", "24:de:c6:07:c2:d1": "Marts 012", "d8:c7:c8:a1:c4:98": "O'Leary 221", "d8:c7:c8:a1:c4:99": "O'Leary 221", "d8:c7:c8:a1:c6:6a": "O'Leary 106", "24:de:c6:07:c2:d0": "Marts 012", "00:1a:1e:22:3a:b1": "Coleman 1st Floor", "d8:c7:c8:a1:24:6a": "Rooke 207", "d8:c7:c8:a1:c4:90": "O'Leary 221", "d8:c7:c8:a1:c4:91": "O'Leary 221", "d8:c7:c8:a1:c4:92": "O'Leary 221", "00:1a:1e:22:32:50": "Rooke 226", "00:1a:1e:23:99:b2": "Olin 266", "00:1a:1e:23:99:c1": "Coleman 2nd Floor", "00:1a:1e:23:99:b0": "Olin 266", "00:1a:1e:23:99:b1": "Olin 266", "00:1a:1e:22:2a:42": "Rooke 2nd Floor", "00:1a:1e:22:2a:40": "Rooke 2nd Floor", "00:1a:1e:22:2a:41": "Rooke 2nd Floor", "00:1a:1e:22:3a:b2": "Coleman 1st Floor", "00:1a:1e:23:98:a0": "Coleman 166", "00:1a:1e:23:98:a1": "Coleman 166", "00:1a:1e:23:98:a2": "Coleman 166", "00:1a:1e:22:3b:91": "Coleman 150", "00:1a:1e:22:3b:90": "Coleman 150", "00:1a:1e:22:3b:92": "Coleman 150", "00:1a:1e:23:99:d1": "Coleman 2nd Floor", "00:1a:1e:22:3b:60": "Breakiron 167", "00:1a:1e:22:3b:61": "Breakiron 167", "00:1a:1e:22:3b:62": "Breakiron 167", "00:1a:1e:22:46:e2": "Coleman 121", "00:1a:1e:22:46:e0": "Coleman 121", "00:1a:1e:22:46:e1": "Coleman 121", "d8:c7:c8:a1:24:60": "Rooke 207", "d8:c7:c8:a1:24:61": "Rooke 207", "d8:c7:c8:a1:24:62": "Rooke 207", "00:1a:1e:22:54:82": "Breakiron 068", "00:1a:1e:22:32:c0": "Rooke 1st Floor", "00:1a:1e:22:54:80": "Breakiron 068", "00:1a:1e:22:54:81": "Breakiron 068", "00:1a:1e:23:99:d2": "Coleman 2nd Floor", "00:1a:1e:22:2f:50": "Dana 224", "00:1a:1e:22:2f:51": "Dana 224", "00:1a:1e:22:2f:52": "Dana 224", "6c:f3:7f:b8:ac:90": "Marts 2nd Floor", "00:1a:1e:22:55:70": "Rooke 116", "00:1a:1e:22:55:71": "Rooke 116", "00:1a:1e:22:51:e2": "Coleman 060", "00:1a:1e:22:51:e0": "Coleman 060", "00:1a:1e:22:51:e1": "Coleman 060", "00:1a:1e:22:55:72": "Rooke 116", "6c:f3:7f:b8:ab:52": "Marts 102C", "00:1a:1e:22:2e:d0": "Coleman Ground Floor", "00:1a:1e:22:2e:d1": "Coleman Ground Floor", "00:1a:1e:22:56:12": "Rooke 323", "00:1a:1e:22:56:11": "Rooke 323", "00:1a:1e:22:56:10": "Rooke 323", "00:1a:1e:22:26:72": "Breakiron B60", "00:1a:1e:22:26:70": "Breakiron B60", "00:1a:1e:22:26:71": "Breakiron B60", "00:1a:1e:22:33:81": "Rooke Ground Floor", "00:1a:1e:22:33:80": "Rooke Ground Floor", "00:1a:1e:22:33:82": "Rooke Ground Floor", "00:1a:1e:22:39:61": "Dana 132", "00:1a:1e:22:39:60": "Dana 132", "00:1a:1e:22:39:62": "Dana 132"}
